{
  "chapter": "1138",
  "part": 3,
  "title": "God’s Knights Open the Abyss",
  "description": "On pages 7–9, this part focuses on Unknown person #7, Nami, Gunko, Unknown person #8, Luffy, Unknown person #9 as Luffy, Zoro, and Nami push toward freeing Loki while Scopper Gaban tests them and God’s Knights begin a darker move against Elbaf’s children.",
  "pages": [
    7,
    8,
    9
  ],
  "characters": [
    "Unknown person #7",
    "Nami",
    "Gunko",
    "Unknown person #8",
    "Luffy",
    "Unknown person #9"
  ],
  "scene": "Luffy, Zoro, and Nami push toward freeing Loki while Scopper Gaban tests them and God’s Knights begin a darker move against Elbaf’s children.",
  "dialogue": [
    {
      "speaker": "Unknown person #7",
      "text": "You've gotta be kidding me..."
    },
    {
      "speaker": "Unknown person #7",
      "text": "Ruff!!"
    },
    {
      "speaker": "Nami",
      "text": "NO WAY!!!"
    },
    {
      "speaker": "Unknown person #7",
      "text": "Ruff!!"
    },
    {
      "speaker": "Unknown person #7",
      "text": "If that thing gets me--!!"
    },
    {
      "speaker": "Unknown person #7",
      "text": "Those celestial bastards!!"
    },
    {
      "speaker": "Unknown person #7",
      "text": "Do you have"
    },
    {
      "speaker": "Unknown person #7",
      "text": "Damn it all!!"
    },
    {
      "speaker": "Unknown person #7",
      "text": "You can"
    },
    {
      "speaker": "Unknown person #7",
      "text": "Total subjudation isn't feasible now."
    },
    {
      "speaker": "Gunko",
      "text": "Let's start by taking their children hostage..."
    },
    {
      "speaker": "Unknown person #7",
      "text": "We'll need an extra person..."
    },
    {
      "speaker": "Unknown person #7",
      "text": "Understood. Who shall I call?"
    },
    {
      "speaker": "Unknown person #8",
      "text": "Quest Castle"
    },
    {
      "speaker": "Unknown person #8",
      "text": "I'm telling you..."
    },
    {
      "speaker": "Unknown person #8",
      "text": "It was red- haired"
    },
    {
      "speaker": "Unknown person #8",
      "text": "Liar!!"
    },
    {
      "speaker": "Luffy",
      "text": "Shanks would never attack for no reason!!"
    },
    {
      "speaker": "Narrator",
      "text": "It's the truth. I saw him with my own eyes."
    },
    {
      "speaker": "Narrator",
      "text": "Red Hair has visited Elbaf many times... I recognized him!"
    },
    {
      "speaker": "Narrator",
      "text": "But I know shanks! He's a super cool guy! Maybe it was just someone who looked like him?"
    },
    {
      "speaker": "Narrator",
      "text": "it was shocking; we were wondering what he was doing in the castle..."
    },
    {
      "speaker": "Narrator",
      "text": "Wouldn't it be weird for him to come right back just to skulk around?"
    },
    {
      "speaker": "Nami",
      "text": "He just left Elbaf recently, right?"
    },
    {
      "speaker": "Narrator",
      "text": "Even if you're telling the truth, there's no way it could be shanks!!"
    },
    {
      "speaker": "Luffy",
      "text": "Shanks is always calm and laid-back!"
    },
    {
      "speaker": "Narrator",
      "text": "him doing something like this just doesn't add up!"
    },
    {
      "speaker": "Narrator",
      "text": "hehe... you really have faith in him, huh?"
    },
    {
      "speaker": "Unknown person #9",
      "text": "You betcha, Nami!"
    },
    {
      "speaker": "Narrator",
      "text": "It'd tick you off just as much if someone badmouthed tell-mere!"
    },
    {
      "speaker": "Unknown person #9",
      "text": "It's Bell- mere- San."
    },
    {
      "speaker": "Unknown person #9",
      "text": "So it was a look- alike?"
    },
    {
      "speaker": "Unknown person #9",
      "text": "that..."
    },
    {
      "speaker": "Unknown person #9",
      "text": "or a brother maybe..."
    },
    {
      "speaker": "Narrator",
      "text": "Shanks' brother??? Well, if he has one, he'd probably be a nice guy, too..."
    },
    {
      "speaker": "Narrator",
      "text": "But honestly... he never talked about his family."
    },
    {
      "speaker": "Narrator",
      "text": "I heard that he was raised on a pirate ship from when he was little..."
    },
    {
      "speaker": "Narrator",
      "text": "I figure Roger and Rayleigh were his real family..."
    },
    {
      "speaker": "Unknown person #9",
      "text": "Their whole crew..."
    },
    {
      "speaker": "Unknown person #9",
      "text": "Except for buggy!"
    },
    {
      "speaker": "Unknown person #9",
      "text": "Step... Step..."
    },
    {
      "speaker": "Unknown person #9",
      "text": "And so"
    }
  ],
  "summary": "This part advances the Scopper Gaban and Elbaf’s New Threat through 42 cleaned dialogue beats, emphasizing the core conflict, character stakes, and transition into the next movement of the story.",
  "confidence": 0.54,
  "needs_review": true
}