{
  "chapter": "356",
  "part": 2,
  "title": "Robin Boards the Sea Train",
  "description": "Luffy and the crew push toward the station as Robin’s forced departure and the storm make every minute matter.",
  "pages": [
    5,
    6,
    7,
    8
  ],
  "characters": [
    "Luffy",
    "Nami",
    "Franky",
    "Zoro",
    "Sanji",
    "Chopper",
    "Usopp",
    "Nico Robin",
    "CP9 agent",
    "Kokoro"
  ],
  "scene": "Across pages 5, 6, 7, 8, this part follows Luffy, Nami, Franky, Zoro, Sanji. Luffy and the crew push toward the station as Robin’s forced departure and the storm make every minute matter.",
  "dialogue": [
    {
      "speaker": "Luffy",
      "text": "HAA..."
    },
    {
      "speaker": "Nami",
      "text": "HAA..."
    },
    {
      "speaker": "Franky",
      "text": "ICE- BURG!!?"
    },
    {
      "speaker": "Nami",
      "text": "Tom- San!!!"
    },
    {
      "speaker": "Zoro",
      "text": "Those are also \"battle frankies\"....!!"
    },
    {
      "speaker": "Sanji",
      "text": "This doesn't make any sense....!!!"
    },
    {
      "speaker": "Franky",
      "text": "Hey, you guys!!!"
    },
    {
      "speaker": "Franky",
      "text": "What's Wrong!! Are you alive??"
    },
    {
      "speaker": "Chopper",
      "text": "... what HAP- penned?!!"
    },
    {
      "speaker": "Franky",
      "text": "HAA"
    },
    {
      "speaker": "Franky",
      "text": "Icebu--..."
    },
    {
      "speaker": "Franky",
      "text": "HAA..."
    },
    {
      "speaker": "Usopp",
      "text": "You ass- hole...!!!"
    },
    {
      "speaker": "Franky",
      "text": "Those guys who came by before"
    },
    {
      "speaker": "Franky",
      "text": "From the invest- gallon group...!!"
    },
    {
      "speaker": "Franky",
      "text": "Your Warships were used by those guys....!!!"
    },
    {
      "speaker": "Franky",
      "text": "......!! All this was done..."
    },
    {
      "speaker": "Usopp",
      "text": "...by my battle- ships!!?"
    },
    {
      "speaker": "Chopper",
      "text": "I said it..."
    },
    {
      "speaker": "Franky",
      "text": "Using my battle- ships"
    },
    {
      "speaker": "Nico Robin",
      "text": "Tom has...!!!"
    }
  ],
  "summary": "Luffy and the crew push toward the station as Robin’s forced departure and the storm make every minute matter.",
  "confidence": 0.84,
  "needs_review": false
}