{
  "chapter": "873",
  "part": 2,
  "title": "Escape From the Chateau",
  "description": "On pages 6–9, this part focuses on Unknown person #5, Streusen, Big Mom, Unknown person #6, Big Mom Pirates, Unknown person #7 as The tea party collapses into chaos as the alliance tries to flee Big Mom’s territory.",
  "pages": [
    6,
    7,
    8,
    9
  ],
  "characters": [
    "Unknown person #5",
    "Streusen",
    "Big Mom",
    "Unknown person #6",
    "Big Mom Pirates",
    "Unknown person #7",
    "Unknown person #8"
  ],
  "scene": "The assassination plan fails and the wedding becomes a desperate escape from a collapsing battlefield.",
  "dialogue": [
    {
      "speaker": "Unknown person #5",
      "text": "Weeed- diningg"
    },
    {
      "speaker": "Unknown person #5",
      "text": "CAAAAAK- KEEEEE!!!"
    },
    {
      "speaker": "Unknown person #5",
      "text": "OH NO!! It'S THE QUEEN'S EATING DISORDER!!!!"
    },
    {
      "speaker": "Unknown person #5",
      "text": "She's having another tantrum again so soon..!"
    },
    {
      "speaker": "Narrator",
      "text": "I just remembered that she couldn't eat the wedding cake, since it got destroyed!!"
    },
    {
      "speaker": "Unknown person #5",
      "text": "That person she's holding in her hand....!!"
    },
    {
      "speaker": "Unknown person #5",
      "text": "It's Brother Opera!!"
    },
    {
      "speaker": "Narrator",
      "text": "Don't tell me that you got your lifespan sucked out!!?"
    },
    {
      "speaker": "Narrator",
      "text": "...!! Even if you're reckless, you should've known not to stand up to her!!"
    },
    {
      "speaker": "Unknown person #5",
      "text": "Nobody else get close to her!!"
    },
    {
      "speaker": "Narrator",
      "text": "You should all know this already!! There's no way to stop Mama's eating dis- order..."
    },
    {
      "speaker": "Narrator",
      "text": "Unless you bring out the food she wants!!!"
    },
    {
      "speaker": "Narrator",
      "text": "Where's the head chef!? He's the only person able to remake the cake!!"
    },
    {
      "speaker": "Streusen",
      "text": "...that's the thing... streusen-sama is.."
    },
    {
      "speaker": "Unknown person #5",
      "text": "Even though he saved every- one's life..."
    },
    {
      "speaker": "Unknown person #5",
      "text": "We"
    },
    {
      "speaker": "Narrator",
      "text": "He failed to make a good landing him- self!!"
    },
    {
      "speaker": "Narrator",
      "text": "It'll take more than a few days for him to recover...!!"
    },
    {
      "speaker": "Narrator",
      "text": "What did you say!? Then how the hell are we going to stop Mama!?"
    },
    {
      "speaker": "Narrator",
      "text": "...It'll be bad to let her rampage in the capital..."
    },
    {
      "speaker": "Unknown person #5",
      "text": "Furthermore, we"
    },
    {
      "speaker": "Big Mom",
      "text": "Mama!! There is a wedding cake!!"
    },
    {
      "speaker": "Unknown person #6",
      "text": "Turns"
    },
    {
      "speaker": "Unknown person #6",
      "text": "brother Peros!! stop! What are you saying!?"
    },
    {
      "speaker": "Big Mom Pirates",
      "text": "There was a spare cake made, Mama!!"
    },
    {
      "speaker": "Narrator",
      "text": "One that was made using carefully selected ingredients. To the point of making you drool..."
    },
    {
      "speaker": "Big Mom",
      "text": "The beest wedding cake (1)"
    },
    {
      "speaker": "Narrator",
      "text": "We wanted Mama to eat it no matter what, but!!"
    },
    {
      "speaker": "Narrator",
      "text": "Shockingly, it was stolen by the straw hat crew!! Perorin~"
    },
    {
      "speaker": "Narrator",
      "text": "Right now, they are trying to escape and are heading towards the south-western bay!!"
    },
    {
      "speaker": "Big Mom",
      "text": "Wedding cake...!!!"
    },
    {
      "speaker": "Unknown person #7",
      "text": "That's right!! They have it!!!"
    },
    {
      "speaker": "Narrator",
      "text": "She should still be able to hear to some extent!! If she goes after them, it'll be two birds with one stone!!"
    },
    {
      "speaker": "Unknown person #7",
      "text": "Steering her away...is it possible?"
    },
    {
      "speaker": "Unknown person #7",
      "text": "If you're lying...!!!"
    },
    {
      "speaker": "Narrator",
      "text": "You'll definitely pay for it with your lifespan..!!!!"
    },
    {
      "speaker": "Unknown person #8",
      "text": "Zeeeuuuuuuuuuuuuuuuuuuuuuuuuuuuuuuuuss!!"
    },
    {
      "speaker": "Big Mom Pirates",
      "text": "Yes, mama!!"
    },
    {
      "speaker": "Unknown person #8",
      "text": "Wedding CAAAAKEE EEEE!!!"
    }
  ],
  "summary": "This section advances the Whole Cake Island Escape storyline with 39 dialogue beats. The alliance survives the failed tea party by turning the chaos into a retreat.",
  "confidence": 0.52,
  "needs_review": true
}