{
  "chapter": "1144",
  "part": 4,
  "title": "Elbaf’s Hidden Corners",
  "description": "On pages 10–12, this part follows Unknown person #10, Robin, Unknown person #11, Loki, Usopp, Unknown person #12 as The Straw Hats explore Elbaf’s strange giant-scale spaces while children, teachers, and old legends point toward the island’s deeper mysteries.",
  "pages": [
    10,
    11,
    12
  ],
  "characters": [
    "Unknown person #10",
    "Robin",
    "Unknown person #11",
    "Loki",
    "Usopp",
    "Unknown person #12",
    "Dorry"
  ],
  "scene": "The Straw Hats explore Elbaf’s strange giant-scale spaces while children, teachers, and old legends point toward the island’s deeper mysteries.",
  "dialogue": [
    {
      "speaker": "Unknown person #10",
      "text": "WAAH!!! Sorry!!"
    },
    {
      "speaker": "Unknown person #10",
      "text": "YLVA!! SKAD!!!"
    },
    {
      "speaker": "Unknown person #10",
      "text": "OLAF!! ya okay back there?!"
    },
    {
      "speaker": "Narrator",
      "text": "What now?! If I stop one they all start pricking each other!!"
    },
    {
      "speaker": "Narrator",
      "text": "That's disgusting!! Who could do such a thing?!"
    },
    {
      "speaker": "Robin",
      "text": "Saul, it must be..."
    },
    {
      "speaker": "Unknown person #10",
      "text": "The work of a fruit ability!!"
    },
    {
      "speaker": "Unknown person #10",
      "text": "They have to be close-by!!"
    },
    {
      "speaker": "Narrator",
      "text": "The kids would reach the fire before we found 'em!!"
    },
    {
      "speaker": "Unknown person #10",
      "text": "We can't let that happen!!"
    },
    {
      "speaker": "Narrator",
      "text": "If we can't stop the one's in front, then we'll start with bjorn in the back!!"
    },
    {
      "speaker": "Unknown person #10",
      "text": "Yes! He's outta the line!"
    },
    {
      "speaker": "Narrator",
      "text": "If I can stop the rest one by one..."
    },
    {
      "speaker": "Unknown person #11",
      "text": "what I find most scary FENRIR"
    },
    {
      "speaker": "Unknown person #11",
      "text": "No way?!"
    },
    {
      "speaker": "Loki",
      "text": "They're actually controlling these monsters too?!"
    },
    {
      "speaker": "Unknown person #11",
      "text": "Who's behind this?!"
    },
    {
      "speaker": "Unknown person #11",
      "text": "G'A!!!"
    },
    {
      "speaker": "Unknown person #11",
      "text": "principal! It's not just Western village..."
    },
    {
      "speaker": "Loki",
      "text": "Other villages are reporting monster sightings!!!"
    },
    {
      "speaker": "Usopp",
      "text": "They're appearing all over Elbaf?!"
    },
    {
      "speaker": "Unknown person #11",
      "text": "It must be some kind of ability."
    },
    {
      "speaker": "Unknown person #11",
      "text": "We need to find them, fast!"
    },
    {
      "speaker": "Unknown person #11",
      "text": "Right!!!"
    },
    {
      "speaker": "Unknown person #11",
      "text": "Western Village Outshirts"
    },
    {
      "speaker": "Unknown person #11",
      "text": "Oombff!"
    },
    {
      "speaker": "Unknown person #11",
      "text": "Finally!"
    },
    {
      "speaker": "Unknown person #11",
      "text": "I didn't think Draugrs were real..."
    },
    {
      "speaker": "Narrator",
      "text": "Who knew taking one down would be this much trouble!"
    },
    {
      "speaker": "Unknown person #11",
      "text": "Carry the injured back to the village!!"
    },
    {
      "speaker": "Unknown person #12",
      "text": "RAAAWR!"
    },
    {
      "speaker": "Unknown person #12",
      "text": "WHAT?!"
    },
    {
      "speaker": "Unknown person #12",
      "text": "BWAHA!!!"
    },
    {
      "speaker": "Unknown person #12",
      "text": "A nidhGGR!"
    },
    {
      "speaker": "Unknown person #12",
      "text": "what I find most scary A NIDHOGGR"
    },
    {
      "speaker": "Unknown person #12",
      "text": "It's no use!! They just keep coming!!"
    },
    {
      "speaker": "Unknown person #12",
      "text": "what I find most scary A GHOST"
    },
    {
      "speaker": "Narrator",
      "text": "We won't be able to protect the village... everyone, take cover!!"
    },
    {
      "speaker": "Dorry",
      "text": "Ready, Dorry?"
    },
    {
      "speaker": "Dorry",
      "text": "Absolutely, Brogy."
    }
  ],
  "summary": "This part advances the Elbaf Exploration through 40 cleaned dialogue beats, focusing on the immediate conflict, character reactions, and the larger Elbaf mystery.",
  "confidence": 0.42,
  "needs_review": true
}