{
  "chapter": "104",
  "part": 5,
  "title": "Luffy Interrupts Laboon’s Grief",
  "description": "On pages 15–18, luffy interrupts laboon’s grief as crocus explains why Laboon keeps hurting himself and reveals the promise that left the whale waiting at Reverse Mountain.",
  "pages": [
    15,
    16,
    17,
    18
  ],
  "characters": [
    "Crocus",
    "Nami",
    "Luffy",
    "Usopp",
    "Zoro",
    "Sanji",
    "Unknown person #1",
    "Unknown person #2",
    "Unknown person #3",
    "Unknown person #4",
    "Laboon"
  ],
  "scene": "Luffy Interrupts Laboon’s Grief. Crocus explains why Laboon keeps hurting himself and reveals the promise that left the whale waiting at Reverse Mountain. The scene focuses on the immediate character conflict rather than background exposition.",
  "dialogue": [
    {
      "speaker": "Crocus",
      "text": "Hey!"
    },
    {
      "speaker": "Crocus",
      "text": "Hey kid!"
    },
    {
      "speaker": "Nami",
      "text": "It's too dangerous!"
    },
    {
      "speaker": "Crocus",
      "text": "don't worry about him, he won't die!"
    },
    {
      "speaker": "Luffy",
      "text": "Puoo Ohhh!"
    },
    {
      "speaker": "Luffy",
      "text": "Heh heh"
    },
    {
      "speaker": "Luffy",
      "text": "You big dummy!"
    },
    {
      "speaker": "Luffy",
      "text": "BOH BOH! HH!"
    },
    {
      "speaker": "Usopp",
      "text": "Aghhh!"
    },
    {
      "speaker": "Luffy",
      "text": "Take this!"
    },
    {
      "speaker": "Zoro",
      "text": "Aghhhh!"
    },
    {
      "speaker": "Crocus",
      "text": "What is he trying to do...?"
    },
    {
      "speaker": "Luffy",
      "text": "Guh!"
    },
    {
      "speaker": "Luffy",
      "text": "Luffy! Just what the hell are you doing!?"
    },
    {
      "speaker": "Nami",
      "text": "Puooo haha!"
    },
    {
      "speaker": "Sanji",
      "text": "It's a tie!"
    },
    {
      "speaker": "Nami",
      "text": "I'm pretty tough, eh?"
    },
    {
      "speaker": "Unknown person #1",
      "text": "Our fight has yet to be settled,"
    },
    {
      "speaker": "Unknown person #2",
      "text": "So we must fight each other again!"
    },
    {
      "speaker": "Unknown person #3",
      "text": "Your old friends may be dead,"
    },
    {
      "speaker": "Unknown person #3",
      "text": "But I'm your new rival!"
    },
    {
      "speaker": "Crocus",
      "text": "And once my crew sails around Grand Line,"
    },
    {
      "speaker": "Unknown person #4",
      "text": "We'll be sure to come back here to see you again."
    },
    {
      "speaker": "Crocus",
      "text": "And then we'll duke it out again!"
    },
    {
      "speaker": "Nami",
      "text": "Boohh! Hhh!"
    }
  ],
  "summary": "This part advances the chapter by focusing on luffy interrupts laboon’s grief. It keeps the main tension clear while preserving the dialogue that drives the scene.",
  "confidence": 0.73,
  "needs_review": true
}