{
  "chapter": "744",
  "part": 3,
  "title": "The Birdcage Covers Dressrosa",
  "description": "Pages 11–15 focus on the birdcage covers dressrosa, keeping the Dressrosa conflict centered on the active characters in this part.",
  "pages": [
    11,
    12,
    13,
    14,
    15
  ],
  "characters": [
    "Unknown person #1",
    "Sabo",
    "Luffy",
    "Unknown person #2",
    "Unknown person #3",
    "Unknown person #4",
    "Doflamingo",
    "Unknown person #5",
    "Unknown person #6",
    "Unknown person #7",
    "Unknown person #8",
    "Unknown person #9",
    "Unknown person #10",
    "Unknown person #11",
    "Unknown person #12",
    "Unknown person #13",
    "Unknown person #14",
    "Unknown person #15",
    "Unknown person #16",
    "Unknown person #17",
    "Unknown person #18",
    "Unknown person #19",
    "Unknown person #20",
    "Unknown person #21",
    "Unknown person #22",
    "Unknown person #23",
    "Doflamingo Family",
    "Trafalgar Law",
    "Unknown person #24",
    "Unknown person #25"
  ],
  "scene": "This part follows Unknown person #1, Sabo, Luffy, Unknown person #2, Unknown person #3, Unknown person #4, Doflamingo as doflamingo traps Dressrosa inside the Birdcage and turns the entire kingdom into a survival game with bounties on his enemies.",
  "dialogue": [
    {
      "speaker": "Unknown person #1",
      "text": "...Anyway. The first Lucy was a 400 million bounty head..."
    },
    {
      "speaker": "Sabo",
      "text": "Oh, and he's my little brother!! Nice to meet you!"
    },
    {
      "speaker": "Luffy",
      "text": "...and the man who's going to be pirate King someday...!! Straw hat Luffy!!"
    },
    {
      "speaker": "Unknown person #2",
      "text": "A pirate?!"
    },
    {
      "speaker": "Sabo",
      "text": "revolutionary army warrior HACK"
    },
    {
      "speaker": "Sabo",
      "text": "revolutionary army - Chief of Staff SABO"
    },
    {
      "speaker": "Unknown person #3",
      "text": "We're the Revo- Lutionsary Army........!!"
    },
    {
      "speaker": "Unknown person #4",
      "text": "Luffy's a pretty swell guy, isn't he? He hasn't changed a bit."
    },
    {
      "speaker": "Doflamingo",
      "text": "What are the Revoli- Tionary Army doing in this country...?"
    },
    {
      "speaker": "Doflamingo",
      "text": "The weapons shipped from this port are supporting wars around the world."
    },
    {
      "speaker": "Unknown person #5",
      "text": "We're here to put a stop to it!!"
    },
    {
      "speaker": "Unknown person #6",
      "text": "The Revolu- Tionary army..."
    },
    {
      "speaker": "Doflamingo",
      "text": "...have sent soldiers into this country many times in the past..."
    },
    {
      "speaker": "Unknown person #7",
      "text": "...but because they were all turned into toys..."
    },
    {
      "speaker": "Unknown person #8",
      "text": "...We haven't been able to expose this black market until now!"
    },
    {
      "speaker": "Unknown person #9",
      "text": "::!!"
    },
    {
      "speaker": "Unknown person #10",
      "text": "Whoa, Whoa, this guy's trouble!!"
    },
    {
      "speaker": "Sabo",
      "text": "That's SABO, isn't it?! What's the number 2 of the revolution- any army doing here?!"
    },
    {
      "speaker": "Doflamingo",
      "text": "We have to tell the young master!!"
    },
    {
      "speaker": "Unknown person #11",
      "text": "...but it looks like the actual \"production\" of the weapons is taking place elsewhere."
    },
    {
      "speaker": "Unknown person #12",
      "text": "Where are they being sourced from........?!"
    },
    {
      "speaker": "Unknown person #13",
      "text": "If we could just find that out..."
    },
    {
      "speaker": "Unknown person #14",
      "text": "...it would make a fine present to take back to dragon-san..."
    },
    {
      "speaker": "Unknown person #15",
      "text": "The Royal Palace."
    },
    {
      "speaker": "Unknown person #16",
      "text": "Aghh!"
    },
    {
      "speaker": "Unknown person #17",
      "text": "Nguaa- AHH!!!"
    },
    {
      "speaker": "Unknown person #18",
      "text": "You one-legged bastard!!!"
    },
    {
      "speaker": "Doflamingo",
      "text": "How dare you kill the young master!!!"
    },
    {
      "speaker": "Unknown person #19",
      "text": "Oin- Guah- Hi!!!"
    },
    {
      "speaker": "Unknown person #20",
      "text": "Buffalo!"
    },
    {
      "speaker": "Unknown person #21",
      "text": "Tra- Dude!!"
    },
    {
      "speaker": "Unknown person #22",
      "text": "I'm here to save you!!"
    },
    {
      "speaker": "Luffy",
      "text": "Straw hat!!"
    },
    {
      "speaker": "Unknown person #23",
      "text": "It's great to see you're alive!"
    },
    {
      "speaker": "Luffy",
      "text": "You shouldn't have any business here, straw hat!!!"
    },
    {
      "speaker": "Doflamingo Family",
      "text": "What of the factory?!! Have you destroyed it?!!"
    },
    {
      "speaker": "Trafalgar Law",
      "text": "Here's the key to his hand- cuffs!!"
    },
    {
      "speaker": "Unknown person #24",
      "text": "You really are well- prepared!! It's like you can see the future!!"
    },
    {
      "speaker": "Luffy",
      "text": "Hold it, straw hat!!"
    },
    {
      "speaker": "Unknown person #25",
      "text": "Violet!!! I won't let you harm the young..."
    },
    {
      "speaker": "Doflamingo",
      "text": "Young Master?!"
    }
  ],
  "summary": "The Birdcage Covers Dressrosa develops the chapter's Dressrosa conflict through Unknown person #1, Sabo, Luffy, Unknown person #2, Unknown person #3, while preserving the OCR dialogue and keeping unclear speakers readable.",
  "confidence": 0.58,
  "needs_review": true
}