{
  "chapter": "1006",
  "part": 3,
  "title": "The Skull Dome Battle Spreads",
  "description": "On pages 11–14, this part focuses on Unknown person #9, Unknown person #10, Yamato, Unknown person #11, Kozuki Alliance, Sanji as Battles spread through the Skull Dome while Tama, Chopper, Marco, and the alliance shift the momentum.",
  "pages": [
    11,
    12,
    13,
    14
  ],
  "characters": [
    "Unknown person #9",
    "Unknown person #10",
    "Yamato",
    "Unknown person #11",
    "Kozuki Alliance",
    "Sanji",
    "Marco",
    "Unknown person #12",
    "Queen",
    "Kaido"
  ],
  "scene": "Across the Skull Dome, the alliance fights to survive while Tama, Chopper, Marco, and the Straw Hats change the flow of battle.",
  "dialogue": [
    {
      "speaker": "Unknown person #9",
      "text": "Listen!! My fellow Yakuza bosses!!"
    },
    {
      "speaker": "Unknown person #9",
      "text": "Huff... huff..."
    },
    {
      "speaker": "Unknown person #9",
      "text": "Yes, great boss!!"
    },
    {
      "speaker": "Unknown person #9",
      "text": "I don't have much time left."
    },
    {
      "speaker": "Unknown person #9",
      "text": "IF TANKI- San doesn't make it..."
    },
    {
      "speaker": "Narrator",
      "text": "...and I'm on the Gusp of turning into an ice demon,"
    },
    {
      "speaker": "Unknown person #9",
      "text": "You must end my life without hesitation!"
    },
    {
      "speaker": "Unknown person #9",
      "text": "IF YOU DON'T..."
    },
    {
      "speaker": "Narrator",
      "text": "I'll end up indiscrimimately killing everyone in this hall."
    },
    {
      "speaker": "Unknown person #9",
      "text": "We can't possibly ....!!"
    },
    {
      "speaker": "Narrator",
      "text": "...He's right. If the boss becomes an ice demon, there'll be not stopping him."
    },
    {
      "speaker": "Unknown person #9",
      "text": "I'm counting on all of you."
    },
    {
      "speaker": "Unknown person #10",
      "text": "Now us ex-mima- warigumi will find out..."
    },
    {
      "speaker": "Unknown person #10",
      "text": "Just how strong..."
    },
    {
      "speaker": "Unknown person #10",
      "text": "This so-called legend is!!"
    },
    {
      "speaker": "Unknown person #10",
      "text": "Isn't that style OBSO- lete!?"
    },
    {
      "speaker": "Unknown person #10",
      "text": "One- Sword flower style..."
    },
    {
      "speaker": "Unknown person #10",
      "text": "You damn geezer!"
    },
    {
      "speaker": "Unknown person #10",
      "text": "...Holy Light!!"
    },
    {
      "speaker": "Unknown person #10",
      "text": "Flery Hair's..."
    },
    {
      "speaker": "Unknown person #10",
      "text": "GAAAAAAAAAAA AAAAM!!!!"
    },
    {
      "speaker": "Yamato",
      "text": "Hehe... you know, oden,"
    },
    {
      "speaker": "Unknown person #11",
      "text": "AAA A!!!!!!"
    },
    {
      "speaker": "Narrator",
      "text": "I used to always wonder how things would've ended up..."
    },
    {
      "speaker": "Narrator",
      "text": "If you and I had challenged Kaido, back when I was in my prime."
    },
    {
      "speaker": "Unknown person #11",
      "text": "but not anymore. Kin'emon and the others..."
    },
    {
      "speaker": "Kozuki Alliance",
      "text": "Did a splendid job executing this raid!!"
    },
    {
      "speaker": "Unknown person #11",
      "text": "And..."
    },
    {
      "speaker": "Unknown person #11",
      "text": "I found myself an interesting protege!!"
    },
    {
      "speaker": "Unknown person #11",
      "text": "Now I know the sun will rise..."
    },
    {
      "speaker": "Narrator",
      "text": "Hey, you gotta be kidding. Hell take out the whole floor if I don't stop him!"
    },
    {
      "speaker": "Unknown person #11",
      "text": "...on Wano again!!"
    },
    {
      "speaker": "Unknown person #11",
      "text": "Damn Geezer!!"
    },
    {
      "speaker": "Sanji",
      "text": "Watch out! Queen-Sama's beam incoming!!"
    },
    {
      "speaker": "Marco",
      "text": "Phoenix Brand!!"
    },
    {
      "speaker": "Unknown person #12",
      "text": "Argh!!"
    },
    {
      "speaker": "Narrator",
      "text": "That hurt, bastard!! was that some sort of shock wave!?!?"
    },
    {
      "speaker": "Unknown person #12",
      "text": "I'm your opponent, remember!?"
    },
    {
      "speaker": "Unknown person #12",
      "text": "Marcotom!"
    },
    {
      "speaker": "Unknown person #12",
      "text": "If you want the Samural..."
    },
    {
      "speaker": "Unknown person #12",
      "text": "...you'll have to kill me first!!"
    }
  ],
  "summary": "This part advances the Wano / Onigashima War storyline through 41 dialogue beats, focusing on the raid’s momentum, character resolve, and the shifting battle lines.",
  "confidence": 0.45,
  "needs_review": true
}