{
  "chapter": "1116",
  "part": 2,
  "title": "The Iron Giant Moves Again",
  "description": "On pages 4–6, this part focuses on Unknown person #4, Unknown person #5, Unknown person #6, Vegapunk as The Straw Hats, Bonney, giants, Vegapunk satellites, and the Iron Giant struggle to escape while the Five Elders press the island from every direction.",
  "pages": [
    4,
    5,
    6
  ],
  "characters": [
    "Unknown person #4",
    "Unknown person #5",
    "Unknown person #6",
    "Vegapunk"
  ],
  "scene": "The Straw Hats, Bonney, giants, Vegapunk satellites, and the Iron Giant struggle to escape while the Five Elders press the island from every direction.",
  "dialogue": [
    {
      "speaker": "Narrator",
      "text": "Edison... is it okay if I let Kaku go free?"
    },
    {
      "speaker": "Narrator",
      "text": "I don't want him to suffer the consequences of this!!!"
    },
    {
      "speaker": "Narrator",
      "text": "Don't worry, I won't let him go after the straw hats... and I don't think pursuing them will be his priority anyway!!!"
    },
    {
      "speaker": "Unknown person #4",
      "text": "UNDER- STOOD, STUSSY!!"
    },
    {
      "speaker": "Narrator",
      "text": "Ahim sorry for puttin' ya through all this."
    },
    {
      "speaker": "Narrator",
      "text": "IT DIDN'T OCCUR TO ME THAT THEY WERE YEAR FRENDS!!!"
    },
    {
      "speaker": "Narrator",
      "text": "FORGVE ME FOR MAKING YA TURN ON 'EM!!"
    },
    {
      "speaker": "Narrator",
      "text": "Despite being torn between both sides, you still rescued us..."
    },
    {
      "speaker": "Narrator",
      "text": "That inner conflict is proof of your humanity, Stussy!"
    },
    {
      "speaker": "Unknown person #4",
      "text": "Do as ya please..."
    },
    {
      "speaker": "Narrator",
      "text": "Just find a way to keep on livin'!!!"
    },
    {
      "speaker": "Unknown person #4",
      "text": "Yes, sir!!"
    },
    {
      "speaker": "Narrator",
      "text": "Two weeks after the flame fragment was stolen..."
    },
    {
      "speaker": "Narrator",
      "text": "We observed an intense glow emamating from above the kingdom of Lulusia..."
    },
    {
      "speaker": "Unknown person #5",
      "text": "UUUSIA!!!"
    },
    {
      "speaker": "Narrator",
      "text": "I later got the news that the entire nation had mysteriously vanished without a trace."
    },
    {
      "speaker": "Narrator",
      "text": "Before long, my equipment registered the worldwide earthquakes I mentioned earlier..."
    },
    {
      "speaker": "Narrator",
      "text": "This might be my pride as a scientist talking, but I was certain of one fact..."
    },
    {
      "speaker": "Unknown person #5",
      "text": "An ancient weapon did that?!"
    },
    {
      "speaker": "Unknown person #5",
      "text": "Why would someone do that to luluia!!!"
    },
    {
      "speaker": "Narrator",
      "text": "Only the mother flame could supply the immense energy needed to cause this tragedy!!"
    },
    {
      "speaker": "Unknown person #5",
      "text": "Lulusia is gone?!"
    },
    {
      "speaker": "Narrator",
      "text": "This is the first we're hearing about this!!!"
    },
    {
      "speaker": "Unknown person #5",
      "text": "hurry and confirm it!!"
    },
    {
      "speaker": "Unknown person #5",
      "text": "Yes, sir!!"
    },
    {
      "speaker": "Narrator",
      "text": "My very own invention was used to power an ancient weapon!!"
    },
    {
      "speaker": "Narrator",
      "text": "The motives and origin of the perpetrators are a mystery to me..."
    },
    {
      "speaker": "Narrator",
      "text": "But in the end, it all boils down to one hard truth."
    },
    {
      "speaker": "Narrator",
      "text": "I am an accessory to this act of mass murder."
    },
    {
      "speaker": "Narrator",
      "text": "I cannot express how remorseful I am for my part in this!! I am truly sorry!!"
    },
    {
      "speaker": "Unknown person #6",
      "text": "But this proves my theory is plausible..."
    },
    {
      "speaker": "Narrator",
      "text": "The disaster that flooded the world was man-made!!"
    },
    {
      "speaker": "Unknown person #6",
      "text": "Vegapunk!!!"
    },
    {
      "speaker": "Unknown person #6",
      "text": "It's not your fault!!"
    },
    {
      "speaker": "Unknown person #6",
      "text": "HUUuh?! then PLUTION IS!!!"
    },
    {
      "speaker": "Unknown person #6",
      "text": "Shushh!!"
    },
    {
      "speaker": "Unknown person #6",
      "text": "Lord MOMONO- Suke!!!"
    },
    {
      "speaker": "Unknown person #6",
      "text": "There were once three great ancient weapons!!!"
    }
  ],
  "summary": "This part advances the Escape from Egghead through 38 cleaned dialogue beats, centering the emotional stakes, battle movement, and the wider consequences of Egghead.",
  "confidence": 0.6,
  "needs_review": false
}