{
  "chapter": "631",
  "part": 1,
  "title": "Luffy Faces Hody",
  "description": "On pages 1–5, this part focuses on Unknown person #1, Unknown person #2, Unknown person #3, Unknown person #4, Unknown person #5, Unknown person #6, Unknown person #7. The core beat is luffy faces hody.",
  "pages": [
    1,
    2,
    3,
    4,
    5
  ],
  "characters": [
    "Unknown person #1",
    "Unknown person #2",
    "Unknown person #3",
    "Unknown person #4",
    "Unknown person #5",
    "Unknown person #6",
    "Unknown person #7",
    "Unknown person #8",
    "Luffy",
    "Hody Jones",
    "Jinbe",
    "Zoro"
  ],
  "scene": "The scene follows luffy faces hody, keeping the focus on Unknown person #1, Unknown person #2, Unknown person #3, Unknown person #4, Unknown person #5, Unknown person #6, Unknown person #7.",
  "dialogue": [
    {
      "speaker": "Narrator",
      "text": "My heart is broken, so I've shaved my head!!!"
    },
    {
      "speaker": "Unknown person #1",
      "text": "Just the top?!!"
    },
    {
      "speaker": "Vander Decken",
      "text": "Fish-Man District, \"Noah\""
    },
    {
      "speaker": "Unknown person #2",
      "text": "CAP'N DECKEN!! You'll get lucky someday!!"
    },
    {
      "speaker": "Unknown person #3",
      "text": "Don't give me empty reassurances, you idiots!!!"
    },
    {
      "speaker": "Narrator",
      "text": "I mean, sure, to begin with, Shirahoshii was still just a kid ..."
    },
    {
      "speaker": "Narrator",
      "text": "...and I only decided to marry her for the sake of fulfilling my ancestors's dream ... but now!!"
    },
    {
      "speaker": "Narrator",
      "text": "\"Not my type\", she said. That was when I realised... truly, this was'love! ...I know it! - didn't fit the metre - by wander decken IX"
    },
    {
      "speaker": "Narrator",
      "text": "And the worst thing is, I still haven't even managed to kill her!"
    },
    {
      "speaker": "Narrator",
      "text": "I can tell that, because the stuff I throw at her still keeps hurtling off into the distance! That straw hat brute is protecting her!!!"
    },
    {
      "speaker": "Unknown person #4",
      "text": "AAA RGHIHHHHHHHHHHHHHHHHHHHHH!!!"
    },
    {
      "speaker": "Unknown person #5",
      "text": "Oh, hang on!"
    },
    {
      "speaker": "Unknown person #6",
      "text": "What wrong cap'n?!"
    },
    {
      "speaker": "Narrator",
      "text": "That's right... I should just crush them all in one fell swoop!"
    },
    {
      "speaker": "Unknown person #7",
      "text": "Every last one of 'em!!"
    },
    {
      "speaker": "Unknown person #8",
      "text": "Bahoh!"
    },
    {
      "speaker": "Narrator",
      "text": "...ohhhh, I just had the most beeeea a beautiful idea!!!"
    },
    {
      "speaker": "Unknown person #8",
      "text": "Baha Hoho Hohoh!!!"
    },
    {
      "speaker": "Unknown person #8",
      "text": "Fish-Man Island, Gyoualley Hills"
    },
    {
      "speaker": "Unknown person #8",
      "text": "So in the end ..."
    },
    {
      "speaker": "Unknown person #8",
      "text": "The sea monsters alone..."
    },
    {
      "speaker": "Unknown person #8",
      "text": "...were enough to anninillate ..."
    },
    {
      "speaker": "Unknown person #8",
      "text": "...the whole Neptune army....!!!"
    },
    {
      "speaker": "Narrator",
      "text": "minister of the right!! Minister of the left!!!"
    },
    {
      "speaker": "Unknown person #8",
      "text": "So close ...!!"
    },
    {
      "speaker": "Unknown person #8",
      "text": "We were so close ...!!!"
    },
    {
      "speaker": "King Neptune",
      "text": "Ohhh, Queen Otohime ....!!!"
    },
    {
      "speaker": "Unknown person #8",
      "text": "At this year's Reverie ..."
    },
    {
      "speaker": "Narrator",
      "text": "...your wishes were finally going to come true ....!!!"
    },
    {
      "speaker": "Unknown person #8",
      "text": "How did it come to this...?!"
    },
    {
      "speaker": "Unknown person #8",
      "text": "Please, lend us your protection ..."
    },
    {
      "speaker": "Unknown person #8",
      "text": "At this rate..."
    },
    {
      "speaker": "Narrator",
      "text": "...in just an hour's time... our beloved King will be murdered .....!!"
    },
    {
      "speaker": "Unknown person #8",
      "text": "Ahhh... please, lend him your protection ....!!!"
    },
    {
      "speaker": "Unknown person #8",
      "text": "Outside GYoncord Plaza"
    },
    {
      "speaker": "Narrator",
      "text": "We can't get in....!! the entrance has been sealed!!"
    },
    {
      "speaker": "Unknown person #8",
      "text": "Your majesty !!!"
    },
    {
      "speaker": "Narrator",
      "text": "I can hear those pirates whooping and howling inside....!!"
    },
    {
      "speaker": "Narrator",
      "text": "Let's climb up to above the plaza! We should be able to see inside!!"
    },
    {
      "speaker": "King Neptune",
      "text": "GYoncord Plaza - execution ground of the King (also the place where queen Otohime was assassination)"
    },
    {
      "speaker": "Narrator",
      "text": "Ah! I'm not sure if this is a good idea."
    },
    {
      "speaker": "Unknown person #8",
      "text": "It's the King!!"
    },
    {
      "speaker": "Unknown person #8",
      "text": "Whoa AAAA!! A Kraken?!"
    },
    {
      "speaker": "Unknown person #8",
      "text": "...My soldiers ...!!"
    },
    {
      "speaker": "Unknown person #8",
      "text": "rrrrr ghhh..."
    },
    {
      "speaker": "Unknown person #8",
      "text": "Remember someone"
    }
  ],
  "summary": "Luffy Faces Hody. This part advances Fish-Man Island’s history and present conflict, tying Otohime and Fisher Tiger’s legacy to Hody’s threat.",
  "confidence": 0.58,
  "needs_review": true
}