{
  "chapter": "575",
  "part": 1,
  "title": "Ace’s Fate and the End of the War",
  "description": "In the Marineford War storyline, this section centers on Unknown person #3, Unknown person #4, Blackbeard, Unknown person #5, Luffy, Unknown person #8 as the scene develops across pages 1–4.",
  "pages": [
    1,
    2,
    3,
    4
  ],
  "characters": [
    "Unknown person #3",
    "Unknown person #4",
    "Blackbeard",
    "Unknown person #5",
    "Luffy",
    "Unknown person #8",
    "Unknown person #1",
    "Unknown person #2",
    "Unknown person #6",
    "Unknown person #7",
    "Unknown person #9"
  ],
  "scene": "This scene advances the Marineford War conflict through Unknown person #3, Unknown person #4, Blackbeard, Unknown person #5, Luffy, focusing on the immediate stakes of ace’s fate and the end of the war.",
  "dialogue": [
    {
      "speaker": "Narrator",
      "text": "From this day forward,"
    },
    {
      "speaker": "Luffy",
      "text": "We're Brothers !!"
    },
    {
      "speaker": "Unknown person #1",
      "text": "It can't be!! Hey!!"
    },
    {
      "speaker": "Unknown person #2",
      "text": "...!! Fire fist Ace is Dead!!"
    },
    {
      "speaker": "Unknown person #3",
      "text": "Strawhat boy!!!"
    },
    {
      "speaker": "Unknown person #3",
      "text": "Hmm!!?"
    },
    {
      "speaker": "Unknown person #4",
      "text": "It's Akainu !!!"
    },
    {
      "speaker": "Unknown person #4",
      "text": "You're next, Strawhat !!!"
    },
    {
      "speaker": "Blackbeard",
      "text": "i won't let you take his life!!!"
    },
    {
      "speaker": "Blackbeard",
      "text": "Squad Leader Marco!!"
    },
    {
      "speaker": "Unknown person #5",
      "text": "Take Ace's brother and go, Jimbe!!!"
    },
    {
      "speaker": "Unknown person #5",
      "text": "Got it !!!"
    },
    {
      "speaker": "Unknown person #5",
      "text": "his life... is ace's living will!!!"
    },
    {
      "speaker": "Luffy",
      "text": "we'll protect him in ace's place!!!"
    },
    {
      "speaker": "Blackbeard",
      "text": "Luffy, Get a grip!!!"
    },
    {
      "speaker": "Blackbeard",
      "text": "Uwoo- Ohhh !!!"
    },
    {
      "speaker": "Unknown person #4",
      "text": "I said those two brothers"
    },
    {
      "speaker": "Unknown person #4",
      "text": "Won't escape!!!"
    },
    {
      "speaker": "Unknown person #5",
      "text": "Akainu!!! Look out!!!"
    },
    {
      "speaker": "Unknown person #6",
      "text": "Hmm?"
    },
    {
      "speaker": "Unknown person #7",
      "text": "Hi!!!! Boss!!!"
    },
    {
      "speaker": "Unknown person #8",
      "text": "Everyone, get away!!!"
    },
    {
      "speaker": "Unknown person #9",
      "text": "\"Mei- you.\""
    },
    {
      "speaker": "Unknown person #3",
      "text": "GU- UUH!!!"
    },
    {
      "speaker": "Unknown person #3",
      "text": "cough!"
    },
    {
      "speaker": "Unknown person #8",
      "text": "th-the boss is mad!!"
    }
  ],
  "summary": "This scene advances the Marineford War conflict through Unknown person #3, Unknown person #4, Blackbeard, Unknown person #5, Luffy, focusing on the immediate stakes of ace’s fate and the end of the war.",
  "confidence": 0.66,
  "needs_review": true
}