{
  "chapter": "1102",
  "part": 2,
  "title": "The Price of Bonney’s Freedom",
  "description": "On pages 5–7, this part focuses on Unknown person #4, Luffy, Unknown person #5, Unknown person #6, World Government as Kuma’s life, Bonney’s childhood, and the cost of Saturn and the World Government’s cruelty reach their emotional center.",
  "pages": [
    5,
    6,
    7
  ],
  "characters": [
    "Unknown person #4",
    "Luffy",
    "Unknown person #5",
    "Unknown person #6",
    "World Government"
  ],
  "scene": "Kuma’s life, Bonney’s childhood, and the cost of Saturn and the World Government’s cruelty reach their emotional center.",
  "dialogue": [
    {
      "speaker": "Unknown person #4",
      "text": "Egghead, New World"
    },
    {
      "speaker": "Unknown person #4",
      "text": "This is unsettling."
    },
    {
      "speaker": "Unknown person #4",
      "text": "You think so?"
    },
    {
      "speaker": "Narrator",
      "text": "Their progression is going as smoothly as your own modifications."
    },
    {
      "speaker": "Narrator",
      "text": "Nevermind that though, did you hear the news? Apparently, some cookies declared war on the world government!!"
    },
    {
      "speaker": "Unknown person #4",
      "text": "What?!"
    },
    {
      "speaker": "Unknown person #4",
      "text": "Dragon has a son?!"
    },
    {
      "speaker": "Narrator",
      "text": "If I'm going to let you study all my memories, there's no point trying to hide it."
    },
    {
      "speaker": "Narrator",
      "text": "A man with rubber powers standing up to the government. What a quick of fate."
    },
    {
      "speaker": "Luffy",
      "text": "He sounds just like my idol, Nika."
    },
    {
      "speaker": "Unknown person #4",
      "text": "PE PE PE! That's true!"
    },
    {
      "speaker": "Unknown person #4",
      "text": "Thriller bark, Grand Line"
    },
    {
      "speaker": "Narrator",
      "text": "The government has given me special orders to wipe you all out..."
    },
    {
      "speaker": "Narrator",
      "text": "That said, I'm sure they'd be satisfied if I only brought them straw hat Luffy's head..."
    },
    {
      "speaker": "Narrator",
      "text": "Hand him over, and I'll spare your lives."
    },
    {
      "speaker": "Unknown person #4",
      "text": "Go to Hell!!!"
    },
    {
      "speaker": "Unknown person #5",
      "text": "What a shame."
    },
    {
      "speaker": "Unknown person #5",
      "text": "URSUS SHOCK."
    },
    {
      "speaker": "Unknown person #5",
      "text": "Luffy is the man..."
    },
    {
      "speaker": "Unknown person #5",
      "text": "...who will become King of the Pirates!"
    },
    {
      "speaker": "Narrator",
      "text": "If you truly mean to take his place..."
    },
    {
      "speaker": "Narrator",
      "text": "...you must be willing to bear all his pain and suffering yourself."
    },
    {
      "speaker": "Narrator",
      "text": "This much damage might be enough to even knock me out..."
    },
    {
      "speaker": "Unknown person #5",
      "text": "He has exceptional friends."
    },
    {
      "speaker": "Unknown person #5",
      "text": "Just as I'd expect of your son..."
    },
    {
      "speaker": "Unknown person #5",
      "text": "Dragon,"
    },
    {
      "speaker": "Unknown person #6",
      "text": "Near the Sabaody archipelago"
    },
    {
      "speaker": "Narrator",
      "text": "We are calling in all seven warlords of the sea!"
    },
    {
      "speaker": "Narrator",
      "text": "If you refuse to come, you'll be forfeiting your title!"
    },
    {
      "speaker": "Unknown person #6",
      "text": "Quite the statement... What's the occasion?"
    },
    {
      "speaker": "Narrator",
      "text": "The flag-bearer of the new era, Portgas D. Ace..."
    },
    {
      "speaker": "Unknown person #6",
      "text": "His public execution date has been set."
    },
    {
      "speaker": "Narrator",
      "text": "This will mean war with the Whitebeard Pirates!!"
    },
    {
      "speaker": "Unknown person #6",
      "text": "war? With the white- beard?!"
    },
    {
      "speaker": "Narrator",
      "text": "I will be sure to arrive before the execution date."
    },
    {
      "speaker": "Unknown person #6",
      "text": "Saboody archipelago"
    },
    {
      "speaker": "Unknown person #6",
      "text": "Where's my food?!"
    },
    {
      "speaker": "Unknown person #6",
      "text": "I'm Wastin' away here!!"
    },
    {
      "speaker": "Unknown person #6",
      "text": "Pizza!!"
    },
    {
      "speaker": "Unknown person #6",
      "text": "BRING!! ME!! MORE!! NOOOW!!!"
    }
  ],
  "summary": "This part advances the Kuma and Bonney Flashback through 40 cleaned dialogue beats, centering the emotional stakes, battle movement, and the wider consequences of Egghead.",
  "confidence": 0.48,
  "needs_review": true
}